[
  {
    "symbol": "AAPL",
    "analyzed_at": "2026-07-13T16:18:43.293647",
    "article_count": 20,
    "average_sentiment": 0.1141,
    "sentiment_trend": "slightly_bullish",
    "momentum": 0.1283,
    "confidence": 0.8359,
    "recommendation": "positive_momentum",
    "positive_articles": 8,
    "negative_articles": 0,
    "neutral_articles": 12
  },
  {
    "symbol": "MSFT",
    "analyzed_at": "2026-07-13T16:18:43.306960",
    "article_count": 20,
    "average_sentiment": 0.1141,
    "sentiment_trend": "slightly_bullish",
    "momentum": -0.0125,
    "confidence": 0.8359,
    "recommendation": "mixed_signals",
    "positive_articles": 8,
    "negative_articles": 0,
    "neutral_articles": 12
  },
  {
    "symbol": "GOOGL",
    "analyzed_at": "2026-07-13T16:18:43.318781",
    "article_count": 20,
    "average_sentiment": 0.1141,
    "sentiment_trend": "slightly_bullish",
    "momentum": -0.1348,
    "confidence": 0.8359,
    "recommendation": "mixed_signals",
    "positive_articles": 8,
    "negative_articles": 0,
    "neutral_articles": 12
  },
  {
    "symbol": "AMZN",
    "analyzed_at": "2026-07-13T16:18:43.331534",
    "article_count": 20,
    "average_sentiment": 0.1141,
    "sentiment_trend": "slightly_bullish",
    "momentum": -0.0742,
    "confidence": 0.8359,
    "recommendation": "mixed_signals",
    "positive_articles": 8,
    "negative_articles": 0,
    "neutral_articles": 12
  },
  {
    "symbol": "META",
    "analyzed_at": "2026-07-13T16:18:43.345347",
    "article_count": 20,
    "average_sentiment": 0.1141,
    "sentiment_trend": "slightly_bullish",
    "momentum": 0.0273,
    "confidence": 0.8359,
    "recommendation": "positive_momentum",
    "positive_articles": 8,
    "negative_articles": 0,
    "neutral_articles": 12
  },
  {
    "symbol": "NVDA",
    "analyzed_at": "2026-07-13T16:18:43.424129",
    "article_count": 20,
    "average_sentiment": 0.1141,
    "sentiment_trend": "slightly_bullish",
    "momentum": -0.0742,
    "confidence": 0.8359,
    "recommendation": "mixed_signals",
    "positive_articles": 8,
    "negative_articles": 0,
    "neutral_articles": 12
  },
  {
    "symbol": "TSLA",
    "analyzed_at": "2026-07-13T16:18:43.436141",
    "article_count": 20,
    "average_sentiment": 0.1141,
    "sentiment_trend": "slightly_bullish",
    "momentum": -0.0871,
    "confidence": 0.8359,
    "recommendation": "mixed_signals",
    "positive_articles": 8,
    "negative_articles": 0,
    "neutral_articles": 12
  },
  {
    "symbol": "JPM",
    "analyzed_at": "2026-07-13T16:18:43.447263",
    "article_count": 20,
    "average_sentiment": 0.1141,
    "sentiment_trend": "slightly_bullish",
    "momentum": -0.0742,
    "confidence": 0.8359,
    "recommendation": "mixed_signals",
    "positive_articles": 8,
    "negative_articles": 0,
    "neutral_articles": 12
  },
  {
    "symbol": "V",
    "analyzed_at": "2026-07-13T16:18:43.458348",
    "article_count": 20,
    "average_sentiment": 0.1141,
    "sentiment_trend": "slightly_bullish",
    "momentum": 0.0242,
    "confidence": 0.8359,
    "recommendation": "positive_momentum",
    "positive_articles": 8,
    "negative_articles": 0,
    "neutral_articles": 12
  },
  {
    "symbol": "JNJ",
    "analyzed_at": "2026-07-13T16:18:43.469387",
    "article_count": 20,
    "average_sentiment": 0.1141,
    "sentiment_trend": "slightly_bullish",
    "momentum": 0.0334,
    "confidence": 0.8359,
    "recommendation": "positive_momentum",
    "positive_articles": 8,
    "negative_articles": 0,
    "neutral_articles": 12
  }
]