[
  {
    "symbol": "AAPL",
    "analyzed_at": "2026-06-30T12:04:03.721408",
    "article_count": 20,
    "average_sentiment": 0.1141,
    "sentiment_trend": "slightly_bullish",
    "momentum": -0.0416,
    "confidence": 0.8359,
    "recommendation": "mixed_signals",
    "positive_articles": 8,
    "negative_articles": 0,
    "neutral_articles": 12
  },
  {
    "symbol": "MSFT",
    "analyzed_at": "2026-06-30T12:04:03.737326",
    "article_count": 20,
    "average_sentiment": 0.1141,
    "sentiment_trend": "slightly_bullish",
    "momentum": -0.0867,
    "confidence": 0.8359,
    "recommendation": "mixed_signals",
    "positive_articles": 8,
    "negative_articles": 0,
    "neutral_articles": 12
  },
  {
    "symbol": "GOOGL",
    "analyzed_at": "2026-06-30T12:04:03.751542",
    "article_count": 20,
    "average_sentiment": 0.1141,
    "sentiment_trend": "slightly_bullish",
    "momentum": 0.0867,
    "confidence": 0.8359,
    "recommendation": "positive_momentum",
    "positive_articles": 8,
    "negative_articles": 0,
    "neutral_articles": 12
  },
  {
    "symbol": "AMZN",
    "analyzed_at": "2026-06-30T12:04:03.765469",
    "article_count": 20,
    "average_sentiment": 0.1141,
    "sentiment_trend": "slightly_bullish",
    "momentum": 0.1076,
    "confidence": 0.8359,
    "recommendation": "positive_momentum",
    "positive_articles": 8,
    "negative_articles": 0,
    "neutral_articles": 12
  },
  {
    "symbol": "META",
    "analyzed_at": "2026-06-30T12:04:03.778997",
    "article_count": 20,
    "average_sentiment": 0.1141,
    "sentiment_trend": "slightly_bullish",
    "momentum": -0.0242,
    "confidence": 0.8359,
    "recommendation": "mixed_signals",
    "positive_articles": 8,
    "negative_articles": 0,
    "neutral_articles": 12
  },
  {
    "symbol": "NVDA",
    "analyzed_at": "2026-06-30T12:04:03.792596",
    "article_count": 20,
    "average_sentiment": 0.1141,
    "sentiment_trend": "slightly_bullish",
    "momentum": -0.0755,
    "confidence": 0.8359,
    "recommendation": "mixed_signals",
    "positive_articles": 8,
    "negative_articles": 0,
    "neutral_articles": 12
  },
  {
    "symbol": "TSLA",
    "analyzed_at": "2026-06-30T12:04:03.806399",
    "article_count": 20,
    "average_sentiment": 0.1141,
    "sentiment_trend": "slightly_bullish",
    "momentum": 0.1348,
    "confidence": 0.8359,
    "recommendation": "positive_momentum",
    "positive_articles": 8,
    "negative_articles": 0,
    "neutral_articles": 12
  },
  {
    "symbol": "JPM",
    "analyzed_at": "2026-06-30T12:04:03.820200",
    "article_count": 20,
    "average_sentiment": 0.1141,
    "sentiment_trend": "slightly_bullish",
    "momentum": 0.0893,
    "confidence": 0.8359,
    "recommendation": "positive_momentum",
    "positive_articles": 8,
    "negative_articles": 0,
    "neutral_articles": 12
  },
  {
    "symbol": "V",
    "analyzed_at": "2026-06-30T12:04:03.834182",
    "article_count": 20,
    "average_sentiment": 0.1141,
    "sentiment_trend": "slightly_bullish",
    "momentum": -0.0742,
    "confidence": 0.8359,
    "recommendation": "mixed_signals",
    "positive_articles": 8,
    "negative_articles": 0,
    "neutral_articles": 12
  },
  {
    "symbol": "JNJ",
    "analyzed_at": "2026-06-30T12:04:03.847705",
    "article_count": 20,
    "average_sentiment": 0.1141,
    "sentiment_trend": "slightly_bullish",
    "momentum": -0.0357,
    "confidence": 0.8359,
    "recommendation": "mixed_signals",
    "positive_articles": 8,
    "negative_articles": 0,
    "neutral_articles": 12
  }
]