[
  {
    "symbol": "AAPL",
    "analyzed_at": "2026-05-26T22:59:15.896900",
    "article_count": 20,
    "average_sentiment": 0.1141,
    "sentiment_trend": "slightly_bullish",
    "momentum": 0.0598,
    "confidence": 0.8359,
    "recommendation": "positive_momentum",
    "positive_articles": 8,
    "negative_articles": 0,
    "neutral_articles": 12
  },
  {
    "symbol": "MSFT",
    "analyzed_at": "2026-05-26T22:59:15.910623",
    "article_count": 20,
    "average_sentiment": 0.1141,
    "sentiment_trend": "slightly_bullish",
    "momentum": -0.0117,
    "confidence": 0.8359,
    "recommendation": "mixed_signals",
    "positive_articles": 8,
    "negative_articles": 0,
    "neutral_articles": 12
  },
  {
    "symbol": "GOOGL",
    "analyzed_at": "2026-05-26T22:59:15.923149",
    "article_count": 20,
    "average_sentiment": 0.1141,
    "sentiment_trend": "slightly_bullish",
    "momentum": -0.0607,
    "confidence": 0.8359,
    "recommendation": "mixed_signals",
    "positive_articles": 8,
    "negative_articles": 0,
    "neutral_articles": 12
  },
  {
    "symbol": "AMZN",
    "analyzed_at": "2026-05-26T22:59:15.936810",
    "article_count": 20,
    "average_sentiment": 0.1141,
    "sentiment_trend": "slightly_bullish",
    "momentum": -0.1135,
    "confidence": 0.8359,
    "recommendation": "mixed_signals",
    "positive_articles": 8,
    "negative_articles": 0,
    "neutral_articles": 12
  },
  {
    "symbol": "META",
    "analyzed_at": "2026-05-26T22:59:15.949371",
    "article_count": 20,
    "average_sentiment": 0.1141,
    "sentiment_trend": "slightly_bullish",
    "momentum": -0.0148,
    "confidence": 0.8359,
    "recommendation": "mixed_signals",
    "positive_articles": 8,
    "negative_articles": 0,
    "neutral_articles": 12
  },
  {
    "symbol": "NVDA",
    "analyzed_at": "2026-05-26T22:59:15.961704",
    "article_count": 20,
    "average_sentiment": 0.1141,
    "sentiment_trend": "slightly_bullish",
    "momentum": 0.0268,
    "confidence": 0.8359,
    "recommendation": "positive_momentum",
    "positive_articles": 8,
    "negative_articles": 0,
    "neutral_articles": 12
  },
  {
    "symbol": "TSLA",
    "analyzed_at": "2026-05-26T22:59:15.973981",
    "article_count": 20,
    "average_sentiment": 0.1141,
    "sentiment_trend": "slightly_bullish",
    "momentum": -0.0393,
    "confidence": 0.8359,
    "recommendation": "mixed_signals",
    "positive_articles": 8,
    "negative_articles": 0,
    "neutral_articles": 12
  },
  {
    "symbol": "JPM",
    "analyzed_at": "2026-05-26T22:59:15.986283",
    "article_count": 20,
    "average_sentiment": 0.1141,
    "sentiment_trend": "slightly_bullish",
    "momentum": 0.051,
    "confidence": 0.8359,
    "recommendation": "positive_momentum",
    "positive_articles": 8,
    "negative_articles": 0,
    "neutral_articles": 12
  },
  {
    "symbol": "V",
    "analyzed_at": "2026-05-26T22:59:15.998896",
    "article_count": 20,
    "average_sentiment": 0.1141,
    "sentiment_trend": "slightly_bullish",
    "momentum": -0.0398,
    "confidence": 0.8359,
    "recommendation": "mixed_signals",
    "positive_articles": 8,
    "negative_articles": 0,
    "neutral_articles": 12
  },
  {
    "symbol": "JNJ",
    "analyzed_at": "2026-05-26T22:59:16.011251",
    "article_count": 20,
    "average_sentiment": 0.1141,
    "sentiment_trend": "slightly_bullish",
    "momentum": -0.087,
    "confidence": 0.8359,
    "recommendation": "mixed_signals",
    "positive_articles": 8,
    "negative_articles": 0,
    "neutral_articles": 12
  }
]