[
  {
    "symbol": "AAPL",
    "analyzed_at": "2026-06-03T23:25:59.225031",
    "article_count": 20,
    "average_sentiment": 0.1141,
    "sentiment_trend": "slightly_bullish",
    "momentum": 0.0607,
    "confidence": 0.8359,
    "recommendation": "positive_momentum",
    "positive_articles": 8,
    "negative_articles": 0,
    "neutral_articles": 12
  },
  {
    "symbol": "MSFT",
    "analyzed_at": "2026-06-03T23:25:59.237524",
    "article_count": 20,
    "average_sentiment": 0.1141,
    "sentiment_trend": "slightly_bullish",
    "momentum": 0.0117,
    "confidence": 0.8359,
    "recommendation": "positive_momentum",
    "positive_articles": 8,
    "negative_articles": 0,
    "neutral_articles": 12
  },
  {
    "symbol": "GOOGL",
    "analyzed_at": "2026-06-03T23:25:59.248912",
    "article_count": 20,
    "average_sentiment": 0.1141,
    "sentiment_trend": "slightly_bullish",
    "momentum": -0.0594,
    "confidence": 0.8359,
    "recommendation": "mixed_signals",
    "positive_articles": 8,
    "negative_articles": 0,
    "neutral_articles": 12
  },
  {
    "symbol": "AMZN",
    "analyzed_at": "2026-06-03T23:25:59.260823",
    "article_count": 20,
    "average_sentiment": 0.1141,
    "sentiment_trend": "slightly_bullish",
    "momentum": 0.0598,
    "confidence": 0.8359,
    "recommendation": "positive_momentum",
    "positive_articles": 8,
    "negative_articles": 0,
    "neutral_articles": 12
  },
  {
    "symbol": "META",
    "analyzed_at": "2026-06-03T23:25:59.272189",
    "article_count": 20,
    "average_sentiment": 0.1141,
    "sentiment_trend": "slightly_bullish",
    "momentum": 0.0541,
    "confidence": 0.8359,
    "recommendation": "positive_momentum",
    "positive_articles": 8,
    "negative_articles": 0,
    "neutral_articles": 12
  },
  {
    "symbol": "NVDA",
    "analyzed_at": "2026-06-03T23:25:59.283310",
    "article_count": 20,
    "average_sentiment": 0.1141,
    "sentiment_trend": "slightly_bullish",
    "momentum": -0.0264,
    "confidence": 0.8359,
    "recommendation": "mixed_signals",
    "positive_articles": 8,
    "negative_articles": 0,
    "neutral_articles": 12
  },
  {
    "symbol": "TSLA",
    "analyzed_at": "2026-06-03T23:25:59.294516",
    "article_count": 20,
    "average_sentiment": 0.1141,
    "sentiment_trend": "slightly_bullish",
    "momentum": 0.0871,
    "confidence": 0.8359,
    "recommendation": "positive_momentum",
    "positive_articles": 8,
    "negative_articles": 0,
    "neutral_articles": 12
  },
  {
    "symbol": "JPM",
    "analyzed_at": "2026-06-03T23:25:59.305855",
    "article_count": 20,
    "average_sentiment": 0.1141,
    "sentiment_trend": "slightly_bullish",
    "momentum": -0.1344,
    "confidence": 0.8359,
    "recommendation": "mixed_signals",
    "positive_articles": 8,
    "negative_articles": 0,
    "neutral_articles": 12
  },
  {
    "symbol": "V",
    "analyzed_at": "2026-06-03T23:25:59.317178",
    "article_count": 20,
    "average_sentiment": 0.1141,
    "sentiment_trend": "slightly_bullish",
    "momentum": 0.0031,
    "confidence": 0.8359,
    "recommendation": "positive_momentum",
    "positive_articles": 8,
    "negative_articles": 0,
    "neutral_articles": 12
  },
  {
    "symbol": "JNJ",
    "analyzed_at": "2026-06-03T23:25:59.328450",
    "article_count": 20,
    "average_sentiment": 0.1141,
    "sentiment_trend": "slightly_bullish",
    "momentum": 0.0148,
    "confidence": 0.8359,
    "recommendation": "positive_momentum",
    "positive_articles": 8,
    "negative_articles": 0,
    "neutral_articles": 12
  }
]